vjobs_ebrandon/__init__.py
vjobs_ebrandon/config.yml
vjobs_ebrandon/main.py
vjobs_ebrandon-0.1.2.dist-info/LICENSE
vjobs_ebrandon-0.1.2.dist-info/METADATA
vjobs_ebrandon-0.1.2.dist-info/WHEEL
vjobs_ebrandon-0.1.2.dist-info/top_level.txt
vjobs_ebrandon-0.1.2.dist-info/RECORD
